<?xml version="1.0" encoding="utf-8"?><toc><breadcrumbs><li><a href="a4ea192b-f073-ecf0-c5f0-3a09e77fd9c2.htm">Docs</a></li><li><a href="a4ea192b-f073-ecf0-c5f0-3a09e77fd9c2.htm">Xenia<wbr />Launcher</a></li><li><a href="325c8c4b-c2cc-a12d-d481-696f1648313b.htm">Base<wbr />Std<wbr />Input<wbr />Event</a></li></breadcrumbs><tocItems><li><a id="99ad8230-6fb8-a622-debf-2e3b620add13" href="99ad8230-6fb8-a622-debf-2e3b620add13.htm">Constructor</a></li><li><a id="4e2a1730-2eb8-ea21-a26a-af690d54ad4f" class="has-submenu" href="4e2a1730-2eb8-ea21-a26a-af690d54ad4f.htm"><span data-tocFile="../toc/IDBAA.xml" class="icon toggle" onclick="ToggleExpandCollapse(this); return false;"><i class="fa fa-angle-right"> </i></span>Methods</a><ul class="toc-menu is-hidden"> </ul></li><li><a id="518ad0b3-9b87-48d6-920a-0d27034b101c" class="has-submenu" href="518ad0b3-9b87-48d6-920a-0d27034b101c.htm"><span data-tocFile="../toc/IDCAA.xml" class="icon toggle" onclick="ToggleExpandCollapse(this); return false;"><i class="fa fa-angle-right"> </i></span>Fields</a><ul class="toc-menu is-hidden"> </ul></li></tocItems></toc>