<?xml version="1.0" encoding="utf-8"?><toc><breadcrumbs><li><a href="a4ea192b-f073-ecf0-c5f0-3a09e77fd9c2.htm">Docs</a></li><li><a href="a4ea192b-f073-ecf0-c5f0-3a09e77fd9c2.htm">Xenia<wbr />Launcher</a></li><li><a href="7ed8c7f7-8885-4fc5-94b3-d47c631c30cd.htm">Ozzz<wbr />Framework.<wbr />Description<wbr />Box</a></li><li><a href="7d1c4577-e9aa-39e7-d26f-d625aba0ab0f.htm">Methods</a></li></breadcrumbs><tocItems><li><a id="113f65d4-9541-c750-e968-efc1d0506d05" href="113f65d4-9541-c750-e968-efc1d0506d05.htm">Add<wbr />New<wbr />Outline</a></li><li><a id="5ed169e5-317d-4795-e907-d3f08275c1ad" class="has-submenu" href="5ed169e5-317d-4795-e907-d3f08275c1ad.htm"><span data-tocFile="../toc/IDBB0PB0A.xml" class="icon toggle" onclick="ToggleExpandCollapse(this); return false;"><i class="fa fa-angle-right"> </i></span>Draw</a><ul class="toc-menu is-hidden"> </ul></li><li><a id="9224c273-b6ef-7464-c4c6-013a2162bf36" class="has-submenu" href="9224c273-b6ef-7464-c4c6-013a2162bf36.htm"><span data-tocFile="../toc/IDCB0PB0A.xml" class="icon toggle" onclick="ToggleExpandCollapse(this); return false;"><i class="fa fa-angle-right"> </i></span>Update</a><ul class="toc-menu is-hidden"> </ul></li></tocItems></toc>